glowworm/__init__.py
glowworm/extend.py
glowworm/main.py
glowworm/pysmart.py
pyglowworm-0.1.6.dist-info/METADATA
pyglowworm-0.1.6.dist-info/WHEEL
pyglowworm-0.1.6.dist-info/top_level.txt
pyglowworm-0.1.6.dist-info/RECORD
